vis_intern/Agent_intern.py
vis_intern/Agent_intern_2.py
vis_intern/Splendor.py
vis_intern/Splendor_v2.py
vis_intern/__init__.py
vis_intern/system/Agent_full.py
vis_intern/system/__init__.py
vis_intern/system/mainFunc.py
vis_intern/system/Agent/__init__.py
vis_intern/system/Agent/An_200922/Agent_player.py
vis_intern/system/Agent/An_200922/__init__.py
vis_intern/system/Agent/An_200922/Data/__init__.py
vis_intern/system/Agent/An_200922/Data/Splendor_v2_79200/Ahih1st.npy
vis_intern/system/Agent/An_200922/Data/Splendor_v2_79200/__init__.py
vis_intern/system/Agent/An_270922/Agent_player.py
vis_intern/system/Agent/An_270922/__init__.py
vis_intern/system/Agent/An_270922/Data/__init__.py
vis_intern/system/Agent/An_270922/Data/Splendor_v2_79200/Ahih1st.npy
vis_intern/system/Agent/An_270922/Data/Splendor_v2_79200/__init__.py
vis_intern/system/Agent/Dat_130922/Agent_player.py
vis_intern/system/Agent/Dat_130922/__init__.py
vis_intern/system/Agent/Dat_130922/Data/__init__.py
vis_intern/system/Agent/Dat_130922/Data/Splendor_v2_79200/Best.npz
vis_intern/system/Agent/Dat_130922/Data/Splendor_v2_79200/__init__.py
vis_intern/system/Agent/Dat_200922/Agent_player.py
vis_intern/system/Agent/Dat_200922/__init__.py
vis_intern/system/Agent/Dat_200922/Data/__init__.py
vis_intern/system/Agent/Dat_200922/Data/Splendor_v2_79200/Best.npz
vis_intern/system/Agent/Dat_200922/Data/Splendor_v2_79200/__init__.py
vis_intern/system/Agent/Dat_270922/Agent_player.py
vis_intern/system/Agent/Dat_270922/__init__.py
vis_intern/system/Agent/Dat_270922/Data/__init__.py
vis_intern/system/Agent/Dat_270922/Data/Splendor_v2_79200/Best.npz
vis_intern/system/Agent/Dat_270922/Data/Splendor_v2_79200/__init__.py
vis_intern/system/Agent/Hieu_130922/Agent_player.py
vis_intern/system/Agent/Hieu_130922/__init__.py
vis_intern/system/Agent/Hieu_130922/Data/__init__.py
vis_intern/system/Agent/Hieu_130922/Data/Splendor_v2_79200/CK_Matran.npy
vis_intern/system/Agent/Hieu_130922/Data/Splendor_v2_79200/__init__.py
vis_intern-0.0.5.dist-info/LICENCE.txt
vis_intern-0.0.5.dist-info/METADATA
vis_intern-0.0.5.dist-info/WHEEL
vis_intern-0.0.5.dist-info/top_level.txt
vis_intern-0.0.5.dist-info/RECORD
